loadenv/__init__.py
loadenv/_common.py
loadenv/types.py
loadenv/_targets/__init__.py
loadenv/_targets/dataclasses.py
loadenv/_targets/enum.py
loadenv-0.1.dist-info/LICENSE
loadenv-0.1.dist-info/WHEEL
loadenv-0.1.dist-info/METADATA
loadenv-0.1.dist-info/RECORD
