Metadata-Version: 2.1
Name: loadenv
Version: 0.1
Summary: Automatically load environment variables into structured Python data
Author-email: Jeremiah Paige <ucodery@gmail.com>
Requires-Python: >=3.6
Classifier: License :: OSI Approved :: MIT License
Requires-Dist: tox ; extra == "test"
Project-URL: Home, https://github.com/ucodery/loadenv
Provides-Extra: test
